tf_livepatch_lr/__init__.py
tf_livepatch_lr/livepatch_lr.py
tf_livepatch_lr/test/livepatch_lr.py
tf_livepatch_lr-0.0.5.dist-info/LICENSE.txt
tf_livepatch_lr-0.0.5.dist-info/METADATA
tf_livepatch_lr-0.0.5.dist-info/WHEEL
tf_livepatch_lr-0.0.5.dist-info/top_level.txt
tf_livepatch_lr-0.0.5.dist-info/RECORD
