Metadata-Version: 2.1
Name: tf-livepatch-lr
Version: 0.0.5
Summary: Simple project which allows you to change the learning rate schedule without stopping the training process (tensorflow only)
Home-page: https://github.com/andrewerf/tf_livepatch_lr
Author: Andrew Aralov
Author-email: andrew-aralov@yandex.ru
License: LICENSE.txt
Platform: UNKNOWN
Classifier: Programming Language :: Python :: 3 :: Only
Classifier: License :: OSI Approved :: MIT License
Classifier: Intended Audience :: Developers
License-File: LICENSE.txt
Requires-Dist: numpy
Requires-Dist: tensorflow
